funcat/VERSION.txt
funcat/__init__.py
funcat/api.py
funcat/context.py
funcat/func.py
funcat/helper.py
funcat/indicators.py
funcat/time_series.py
funcat/utils.py
funcat/data/__init__.py
funcat/data/backend.py
funcat/data/rqalpha_data_backend.py
funcat/data/rqdata_data_backend.py
funcat/data/tushare_backend.py
rqfuncat-0.3.3.dist-info/METADATA
rqfuncat-0.3.3.dist-info/RECORD
rqfuncat-0.3.3.dist-info/WHEEL
rqfuncat-0.3.3.dist-info/top_level.txt
