Metadata-Version: 2.1
Name: rqfuncat
Version: 0.3.3
Summary: funcat
Home-page: https://github.com/cedricporter/funcat
Author: Hua Liang, Zirui Wei
Author-email: et@everet.org, ziruiwei@gmail.com
License: Apache License v2
Platform: UNKNOWN
Classifier: Programming Language :: Python
Classifier: Operating System :: Microsoft :: Windows
Classifier: Operating System :: Unix
Classifier: Programming Language :: Python :: 2.7
Classifier: Programming Language :: Python :: 3.4
Classifier: Programming Language :: Python :: 3.5
Classifier: Programming Language :: Python :: 3.6
Requires-Dist: numpy
Requires-Dist: six
Requires-Dist: backports.functools-lru-cache
Requires-Dist: pandas
Requires-Dist: lxml
Requires-Dist: requests
Requires-Dist: TA-Lib
Requires-Dist: cached-property
